soupcan/__init__.py
soupcan/core.py
soupcan-0.0.2.dev0.dist-info/LICENSE
soupcan-0.0.2.dev0.dist-info/METADATA
soupcan-0.0.2.dev0.dist-info/WHEEL
soupcan-0.0.2.dev0.dist-info/top_level.txt
soupcan-0.0.2.dev0.dist-info/RECORD
