Metadata-Version: 2.1
Name: soupcan
Version: 0.0.2.dev0
Summary: simplifies the process of designing a Python tool for extracting and displaying webpage content.
Home-page: https://github.com/stephenmccalman/soupcan
Author: Stephen McCalman
Author-email: stephen.mccalman@gmail.com
License: BSD 3-Clause License
Project-URL: Bug Tracker, https://github.com/stephenmccalman/soupcan/issues
Platform: UNKNOWN
Classifier: Programming Language :: Python :: 3.6
Classifier: Programming Language :: Python :: 3.7
Classifier: Programming Language :: Python :: 3.8
Classifier: License :: OSI Approved :: BSD License
Classifier: Development Status :: 4 - Beta
Requires-Python: >=3.6
License-File: LICENSE
Requires-Dist: beautifulsoup4
